fastscaff/__init__.py
fastscaff/cli.py
fastscaff/generator.py
fastscaff/introspector.py
fastscaff/model_generator.py
fastscaff/templates/app/__init__.py
fastscaff/templates/app/main_sqlalchemy.py
fastscaff/templates/app/main_tortoise.py
fastscaff/templates/app/api/__init__.py
fastscaff/templates/app/api/v1/__init__.py
fastscaff/templates/app/api/v1/router.py
fastscaff/templates/app/api/v1/endpoints/__init__.py
fastscaff/templates/app/api/v1/endpoints/auth.py
fastscaff/templates/app/api/v1/endpoints/health.py
fastscaff/templates/app/api/v1/endpoints/users.py
fastscaff/templates/app/core/__init__.py
fastscaff/templates/app/core/config.py.jinja2
fastscaff/templates/app/core/database_sqlalchemy.py
fastscaff/templates/app/core/database_tortoise.py
fastscaff/templates/app/core/lifespan.py.jinja2
fastscaff/templates/app/core/logger.py.jinja2
fastscaff/templates/app/core/rbac.py
fastscaff/templates/app/core/redis.py
fastscaff/templates/app/core/security.py
fastscaff/templates/app/core/singleton.py
fastscaff/templates/app/exceptions/__init__.py
fastscaff/templates/app/exceptions/base.py
fastscaff/templates/app/exceptions/handlers.py
fastscaff/templates/app/middleware/__init___sqlalchemy.py
fastscaff/templates/app/middleware/__init___tortoise.py
fastscaff/templates/app/middleware/cors.py
fastscaff/templates/app/middleware/database.py
fastscaff/templates/app/middleware/jwt.py
fastscaff/templates/app/middleware/logging.py
fastscaff/templates/app/middleware/security.py
fastscaff/templates/app/middleware/sign.py
fastscaff/templates/app/middleware/tracing.py
fastscaff/templates/app/models/__init__.py
fastscaff/templates/app/models/base_sqlalchemy.py
fastscaff/templates/app/models/base_tortoise.py
fastscaff/templates/app/models/user_sqlalchemy.py
fastscaff/templates/app/models/user_tortoise.py
fastscaff/templates/app/repositories/__init__.py
fastscaff/templates/app/repositories/base_sqlalchemy.py
fastscaff/templates/app/repositories/base_tortoise.py
fastscaff-0.2.0.dist-info/METADATA
fastscaff-0.2.0.dist-info/WHEEL
fastscaff-0.2.0.dist-info/entry_points.txt
fastscaff-0.2.0.dist-info/top_level.txt
fastscaff-0.2.0.dist-info/RECORD
